{
  "seeds": [
    "roadmap-concepts"
  ],
  "mode": "explore",
  "wave": 0,
  "items": [],
  "completed": [
    {
      "file": "symbols/fall-of-babylon.md",
      "type": "symbol-study",
      "hop": 0,
      "completed_at": "2026-02-11T19:17:47.496Z"
    },
    {
      "file": "symbols/return-of-christ.md",
      "type": "symbol-study",
      "hop": 0,
      "completed_at": "2026-02-11T19:18:26.705Z"
    },
    {
      "file": "symbols/rapture-gathering.md",
      "type": "symbol-study",
      "hop": 0,
      "completed_at": "2026-02-11T19:19:03.361Z"
    },
    {
      "file": "symbols/sudden-destruction.md",
      "type": "symbol-study",
      "hop": 0,
      "completed_at": "2026-02-11T19:19:39.601Z"
    },
    {
      "file": "symbols/days-of-noah.md",
      "type": "symbol-study",
      "hop": 0,
      "completed_at": "2026-02-11T19:20:15.410Z"
    },
    {
      "file": "symbols/third-day.md",
      "type": "symbol-study",
      "hop": 0,
      "completed_at": "2026-02-11T19:20:51.743Z"
    },
    {
      "file": "symbols/day-as-1000-years.md",
      "type": "symbol-study",
      "hop": 0,
      "completed_at": "2026-02-11T19:21:27.518Z"
    }
  ],
  "stats": {
    "total_symbols": 56,
    "budget_spent": 0.7
  }
}